Metadata-Version: 1.0
Name: binary-search-module
Version: 1.0.0
Summary: Package of binary search method
Home-page: UNKNOWN
Author: Kirill Borisyuk
Author-email: hurricanekba@gmail.com
License: UNKNOWN
Platform: UNKNOWN
